{
  "formatVersion": 1,
  "database": {
    "version": 1,
    "identityHash": "91563d828976769fdb069ad52705db3c",
    "entities": [
      {
        "tableName": "Question",
        "createSql": "CREATE TABLE IF NOT EXISTS `${TABLE_NAME}` (`id` TEXT NOT NULL, `categoryId` TEXT NOT NULL, `content` TEXT NOT NULL, `image` TEXT NOT NULL, `correct` INTEGER NOT NULL, PRIMARY KEY(`id`))",
        "fields": [
          {
            "fieldPath": "id",
            "columnName": "id",
            "affinity": "TEXT",
            "notNull": true
          },
          {
            "fieldPath": "categoryId",
            "columnName": "categoryId",
            "affinity": "TEXT",
            "notNull": true
          },
          {
            "fieldPath": "content",
            "columnName": "content",
            "affinity": "TEXT",
            "notNull": true
          },
          {
            "fieldPath": "image",
            "columnName": "image",
            "affinity": "TEXT",
            "notNull": true
          },
          {
            "fieldPath": "correct",
            "columnName": "correct",
            "affinity": "INTEGER",
            "notNull": true
          }
        ],
        "primaryKey": {
          "autoGenerate": false,
          "columnNames": [
            "id"
          ]
        }
      }
    ],
    "setupQueries": [
      "CREATE TABLE IF NOT EXISTS room_master_table (id INTEGER PRIMARY KEY,identity_hash TEXT)",
      "INSERT OR REPLACE INTO room_master_table (id,identity_hash) VALUES(42, '91563d828976769fdb069ad52705db3c')"
    ]
  }
}